{
	"configurations" : 
	[
		{
			"directories" : 
			[
				{
					"build" : ".",
					"hasInstallRule" : true,
					"jsonFile" : "directory-.-8dcc10b75a3fa7246ba1.json",
					"minimumCMakeVersion" : 
					{
						"string" : "3.12"
					},
					"projectIndex" : 0,
					"source" : ".",
					"targetIndexes" : 
					[
						0,
						1
					]
				}
			],
			"name" : "",
			"projects" : 
			[
				{
					"directoryIndexes" : 
					[
						0
					],
					"name" : "robotnik_interfaces",
					"targetIndexes" : 
					[
						0,
						1
					]
				}
			],
			"targets" : 
			[
				{
					"directoryIndex" : 0,
					"id" : "robotnik_interfaces_uninstall::@6890427a1f51a3e7e1df",
					"jsonFile" : "target-robotnik_interfaces_uninstall-92f415649ccb91537e2f.json",
					"name" : "robotnik_interfaces_uninstall",
					"projectIndex" : 0
				},
				{
					"directoryIndex" : 0,
					"id" : "uninstall::@6890427a1f51a3e7e1df",
					"jsonFile" : "target-uninstall-49ebe37c6ccc08b53c5b.json",
					"name" : "uninstall",
					"projectIndex" : 0
				}
			]
		}
	],
	"kind" : "codemodel",
	"paths" : 
	{
		"build" : "/home/admin/ros2_ws/build/robotnik_interfaces",
		"source" : "/home/admin/ros2_ws/src/robotnik_interfaces/robotnik_interfaces"
	},
	"version" : 
	{
		"major" : 2,
		"minor" : 3
	}
}
